evrmail/__init__.py
evrmail/cli.py
evrmail/config.py
evrmail/crypto.py
evrmail/decode_message.py
evrmail/encode_message.py
evrmail/launcher.py
evrmail/start_gui.py
evrmail/commands/__init__.py
evrmail/commands/addresses/__init__.py
evrmail/commands/addresses/active.py
evrmail/commands/addresses/dumpprivkey.py
evrmail/commands/addresses/get.py
evrmail/commands/addresses/list.py
evrmail/commands/addresses/publickey.py
evrmail/commands/addresses/rename.py
evrmail/commands/addresses/use.py
evrmail/commands/addresses/validate.py
evrmail/commands/balance/__init__.py
evrmail/commands/contacts/__init__.py
evrmail/commands/contacts/add.py
evrmail/commands/contacts/list.py
evrmail/commands/contacts/remove.py
evrmail/commands/dev/__init__.py
evrmail/commands/inbox/__init__.py
evrmail/commands/inbox/delete.py
evrmail/commands/inbox/filter.py
evrmail/commands/inbox/list.py
evrmail/commands/inbox/mark_read.py
evrmail/commands/inbox/open.py
evrmail/commands/inbox/unread.py
evrmail/commands/ipfs/__init__.py
evrmail/commands/logs/__init__.py
evrmail/commands/logs/logs.py
evrmail/commands/receive/__init__.py
evrmail/commands/send/__init__.py
evrmail/commands/send/send_asset.py
evrmail/commands/send/send_evr.py
evrmail/commands/send/send_msg.py
evrmail/commands/tx/__init__.py
evrmail/commands/wallets/__init__.py
evrmail/commands/wallets/create.py
evrmail/commands/wallets/export.py
evrmail/commands/wallets/list.py
evrmail/commands/wallets/lmport.py
evrmail/commands/wallets/show.py
evrmail/daemon/__init__.py
evrmail/daemon/__main__.py
evrmail/daemon/forwarder.py
evrmail/daemon/shared.py
evrmail/daemon/smtp.py
evrmail/daemon/tunnel.py
evrmail/gui/functions.py
evrmail/gui/gui.py
evrmail/gui/start_gui.py
evrmail/server/mailserver.py
evrmail/utils/__init__.py
evrmail/utils/create_batch_payload.py
evrmail/utils/create_message_payload.py
evrmail/utils/debug_contacts.py
evrmail/utils/decrypt_message.py
evrmail/utils/decrypt_payload_message.py
evrmail/utils/encrypt_message.py
evrmail-0.1.25.dist-info/METADATA
evrmail-0.1.25.dist-info/WHEEL
evrmail-0.1.25.dist-info/entry_points.txt
evrmail-0.1.25.dist-info/top_level.txt
evrmail-0.1.25.dist-info/RECORD
