Metadata-Version: 2.4
Name: evrmail
Version: 0.1.25
Summary: Encrypted messaging over Evrmore
Author: Manticore Technologies LLC
Requires-Python: >=3.10
Requires-Dist: typer[all]
Requires-Dist: coincurve
Requires-Dist: base58
Requires-Dist: pycryptodome
Requires-Dist: requests
Requires-Dist: cryptography
Requires-Dist: textual
Requires-Dist: evrmore_rpc
Requires-Dist: zmq
Requires-Dist: watchdog
Requires-Dist: mnemonic
Requires-Dist: hdwallet
Requires-Dist: python-evrmorelib
Requires-Dist: pyqt5
Requires-Dist: pyqtwebengine
